odoo10_addon_l10n_es_dua_sii-10.0.1.0.1-nspkg.pth
odoo/addons/l10n_es_dua_sii/README.rst
odoo/addons/l10n_es_dua_sii/__init__.py
odoo/addons/l10n_es_dua_sii/__manifest__.py
odoo/addons/l10n_es_dua_sii/i18n/bg.po
odoo/addons/l10n_es_dua_sii/i18n/ca.po
odoo/addons/l10n_es_dua_sii/i18n/cs.po
odoo/addons/l10n_es_dua_sii/i18n/es.po
odoo/addons/l10n_es_dua_sii/i18n/es_CR.po
odoo/addons/l10n_es_dua_sii/i18n/es_ES.po
odoo/addons/l10n_es_dua_sii/i18n/fr.po
odoo/addons/l10n_es_dua_sii/i18n/gl.po
odoo/addons/l10n_es_dua_sii/i18n/hr.po
odoo/addons/l10n_es_dua_sii/i18n/l10n_es_dua_sii.pot
odoo/addons/l10n_es_dua_sii/i18n/nl.po
odoo/addons/l10n_es_dua_sii/i18n/pl.po
odoo/addons/l10n_es_dua_sii/i18n/pt.po
odoo/addons/l10n_es_dua_sii/i18n/pt_BR.po
odoo/addons/l10n_es_dua_sii/i18n/ru.po
odoo/addons/l10n_es_dua_sii/i18n/sl.po
odoo/addons/l10n_es_dua_sii/i18n/sv.po
odoo/addons/l10n_es_dua_sii/i18n/tr.po
odoo/addons/l10n_es_dua_sii/models/__init__.py
odoo/addons/l10n_es_dua_sii/models/account_invoice.py
odoo/addons/l10n_es_dua_sii/static/description/icon.png
odoo10_addon_l10n_es_dua_sii-10.0.1.0.1.dist-info/METADATA
odoo10_addon_l10n_es_dua_sii-10.0.1.0.1.dist-info/WHEEL
odoo10_addon_l10n_es_dua_sii-10.0.1.0.1.dist-info/namespace_packages.txt
odoo10_addon_l10n_es_dua_sii-10.0.1.0.1.dist-info/top_level.txt
odoo10_addon_l10n_es_dua_sii-10.0.1.0.1.dist-info/RECORD
