Metadata-Version: 2.1
Name: odoo10-addon-l10n-es-dua-sii
Version: 10.0.1.0.1
Summary: Suministro Inmediato de Información de importaciones con DUA
Home-page: https://odoo-community.org/
Author: Studio73, Comunitea, Odoo Community Association (OCA)
Author-email: support@odoo-community.org
License: AGPL-3
Platform: UNKNOWN
Classifier: Programming Language :: Python
Classifier: Framework :: Odoo
Classifier: License :: OSI Approved :: GNU Affero General Public License v3
Requires-Python: ~=2.7
Requires-Dist: odoo10-addon-l10n-es-aeat-sii
Requires-Dist: odoo10-addon-l10n-es-dua
Requires-Dist: odoo (<10.1dev,>=10.0)
